Disassembly of _fun:
              0 COPY_FREE_VARS           3
              2 MAKE_CELL                0 (v)
              4 MAKE_CELL                1 (p)

588           6 RESUME                   0
              8 LOAD_GLOBAL              1 (NULL + any)
             18 LOAD_CLOSURE             1 (p)
             20 LOAD_CLOSURE             0 (v)
             22 BUILD_TUPLE              2
             24 LOAD_CONST               1 (<code object <genexpr> at 0x754d4a1af690, file "/home/fabien/DEV/GIT/dsv/json-model/json_model/dynamic.py", line 588>)
             26 MAKE_FUNCTION            8 (closure)
             28 LOAD_DEREF               4 (subs)
             30 GET_ITER
             32 CALL                     0
             40 CALL                     1
             48 COPY                     1
             50 POP_JUMP_IF_TRUE        19 (to 90)
             52 POP_TOP

589          54 LOAD_DEREF               3 (self)
             56 LOAD_ATTR                3 (NULL|self + _no)
             76 LOAD_DEREF               2 (mp)
             78 LOAD_DEREF               1 (p)
             80 LOAD_CONST               2 ('no any matched')
             82 CALL                     3

588     >>   90 RETURN_VALUE

Disassembly of <code object <genexpr> at 0x754d4a1af690, file "/home/fabien/DEV/GIT/dsv/json-model/json_model/dynamic.py", line 588>:
              0 COPY_FREE_VARS           2

588           2 RETURN_GENERATOR
              4 POP_TOP
              6 RESUME                   0
              8 LOAD_FAST                0 (.0)
        >>   10 FOR_ITER                13 (to 40)
             14 STORE_FAST               1 (f)
             16 PUSH_NULL
             18 LOAD_FAST                1 (f)
             20 LOAD_DEREF               3 (v)
             22 LOAD_DEREF               2 (p)
             24 CALL                     2
             32 YIELD_VALUE              1
             34 RESUME                   1
             36 POP_TOP
             38 JUMP_BACKWARD           15 (to 10)
        >>   40 END_FOR
             42 RETURN_CONST             0 (None)
        >>   44 CALL_INTRINSIC_1         3 (INTRINSIC_STOPITERATION_ERROR)
             46 RERAISE                  1
ExceptionTable:
  6 to 42 -> 44 [0] lasti

None
