#
# json model 0
#
              0 COPY_FREE_VARS           3

              2 RESUME                   0
              4 LOAD_GLOBAL              1 (NULL + type)
             14 LOAD_FAST                0 (v)
             16 CALL                     1
             24 LOAD_GLOBAL              2 (int)
             34 IS_OP                    0
             36 COPY                     1
             38 POP_JUMP_IF_FALSE        5 (to 50)
             40 POP_TOP
             42 LOAD_FAST                0 (v)
             44 LOAD_DEREF               4 (val)
             46 COMPARE_OP              40 (==)
        >>   50 COPY                     1
             52 POP_JUMP_IF_TRUE        22 (to 98)
             54 POP_TOP

             56 LOAD_DEREF               3 (self)
             58 LOAD_ATTR                5 (NULL|self + _no)
             78 LOAD_DEREF               2 (mpath)
             80 LOAD_FAST                1 (p)
             82 LOAD_CONST               1 ('expecting integer ')
             84 LOAD_DEREF               4 (val)
             86 FORMAT_VALUE             0
             88 BUILD_STRING             2
             90 CALL                     3

        >>   98 RETURN_VALUE

#
# json model 1
#
              0 COPY_FREE_VARS           3

              2 RESUME                   0
              4 LOAD_GLOBAL              1 (NULL + type)
             14 LOAD_FAST                0 (v)
             16 CALL                     1
             24 LOAD_GLOBAL              2 (int)
             34 IS_OP                    0
             36 COPY                     1
             38 POP_JUMP_IF_FALSE        5 (to 50)
             40 POP_TOP
             42 LOAD_FAST                0 (v)
             44 LOAD_DEREF               4 (val)
             46 COMPARE_OP              40 (==)
        >>   50 COPY                     1
             52 POP_JUMP_IF_TRUE        22 (to 98)
             54 POP_TOP

             56 LOAD_DEREF               3 (self)
             58 LOAD_ATTR                5 (NULL|self + _no)
             78 LOAD_DEREF               2 (mpath)
             80 LOAD_FAST                1 (p)
             82 LOAD_CONST               1 ('expecting integer ')
             84 LOAD_DEREF               4 (val)
             86 FORMAT_VALUE             0
             88 BUILD_STRING             2
             90 CALL                     3

        >>   98 RETURN_VALUE

