Disassembly of _fun:
              0 COPY_FREE_VARS           2

582           2 RESUME                   0
              4 PUSH_NULL
              6 LOAD_DEREF               2 (val_check)
              8 LOAD_FAST                0 (v)
             10 LOAD_FAST                1 (p)
             12 CALL                     2
             20 COPY                     1
             22 POP_JUMP_IF_FALSE        9 (to 42)
             24 POP_TOP
             26 PUSH_NULL
             28 LOAD_DEREF               3 (val_cons)
             30 LOAD_FAST                0 (v)
             32 LOAD_FAST                1 (p)
             34 CALL                     2
        >>   42 RETURN_VALUE

None
