#
# json model 1
#
              0 COPY_FREE_VARS           4

              2 RESUME                   0

              4 LOAD_GLOBAL              1 (NULL + isinstance)
             14 LOAD_FAST                0 (v)
             16 LOAD_GLOBAL              2 (list)
             26 LOAD_GLOBAL              4 (tuple)
             36 BUILD_TUPLE              2
             38 CALL                     2
             46 POP_JUMP_IF_TRUE        19 (to 86)

             48 LOAD_DEREF               6 (self)
             50 LOAD_ATTR                7 (NULL|self + _no)
             70 LOAD_DEREF               4 (mpath)
             72 LOAD_FAST                1 (p)
             74 LOAD_CONST               1 ('expecting an array')
             76 CALL                     3
             84 RETURN_VALUE

        >>   86 LOAD_GLOBAL              9 (NULL + len)
             96 LOAD_FAST                0 (v)
             98 CALL                     1
            106 LOAD_DEREF               5 (nmodels)
            108 COMPARE_OP              55 (!=)
            112 POP_JUMP_IF_FALSE       19 (to 152)

            114 LOAD_DEREF               6 (self)
            116 LOAD_ATTR                7 (NULL|self + _no)
            136 LOAD_DEREF               4 (mpath)
            138 LOAD_FAST                1 (p)
            140 LOAD_CONST               2 ('bad array length')
            142 CALL                     3
            150 RETURN_VALUE

        >>  152 LOAD_GLOBAL             11 (NULL + all)
            162 LOAD_GLOBAL             13 (NULL + range)
            172 LOAD_DEREF               5 (nmodels)
            174 CALL                     1
            182 GET_ITER
            184 LOAD_FAST_AND_CLEAR      2 (i)
            186 SWAP                     2
            188 BUILD_LIST               0
            190 SWAP                     2
        >>  192 FOR_ITER                23 (to 242)
            196 STORE_FAST               2 (i)
            198 PUSH_NULL
            200 LOAD_DEREF               3 (items)
            202 LOAD_FAST                2 (i)
            204 BINARY_SUBSCR
            208 LOAD_FAST                0 (v)
            210 LOAD_FAST                2 (i)
            212 BINARY_SUBSCR
            216 LOAD_FAST                1 (p)
            218 FORMAT_VALUE             0
            220 LOAD_CONST               3 ('[')
            222 LOAD_FAST                2 (i)
            224 FORMAT_VALUE             0
            226 LOAD_CONST               4 (']')
            228 BUILD_STRING             4
            230 CALL                     2
            238 LIST_APPEND              2
            240 JUMP_BACKWARD           25 (to 192)
        >>  242 END_FOR
            244 SWAP                     2
            246 STORE_FAST               2 (i)
            248 CALL                     1
            256 RETURN_VALUE
        >>  258 SWAP                     2
            260 POP_TOP
            262 SWAP                     2
            264 STORE_FAST               2 (i)
            266 RERAISE                  0
ExceptionTable:
  188 to 242 -> 258 [4]

#
# json model 5
#
              0 COPY_FREE_VARS           3

              2 RESUME                   0
              4 LOAD_GLOBAL              1 (NULL + isinstance)
             14 LOAD_FAST                0 (v)
             16 LOAD_GLOBAL              2 (str)
             26 CALL                     2
             34 COPY                     1
             36 POP_JUMP_IF_FALSE        5 (to 48)
             38 POP_TOP
             40 LOAD_FAST                0 (v)
             42 LOAD_DEREF               3 (name)
             44 COMPARE_OP              40 (==)
        >>   48 COPY                     1
             50 POP_JUMP_IF_TRUE        22 (to 96)
             52 POP_TOP

             54 LOAD_DEREF               4 (self)
             56 LOAD_ATTR                5 (NULL|self + _no)
             76 LOAD_DEREF               2 (mpath)
             78 LOAD_FAST                1 (p)
             80 LOAD_CONST               1 ('expecting string ')
             82 LOAD_DEREF               3 (name)
             84 FORMAT_VALUE             0
             86 BUILD_STRING             2
             88 CALL                     3

        >>   96 RETURN_VALUE

#
# json model 6
#
              0 COPY_FREE_VARS           3

              2 RESUME                   0
              4 LOAD_GLOBAL              1 (NULL + isinstance)
             14 LOAD_FAST                0 (v)
             16 LOAD_GLOBAL              2 (str)
             26 CALL                     2
             34 COPY                     1
             36 POP_JUMP_IF_FALSE        5 (to 48)
             38 POP_TOP
             40 LOAD_FAST                0 (v)
             42 LOAD_DEREF               3 (name)
             44 COMPARE_OP              40 (==)
        >>   48 COPY                     1
             50 POP_JUMP_IF_TRUE        22 (to 96)
             52 POP_TOP

             54 LOAD_DEREF               4 (self)
             56 LOAD_ATTR                5 (NULL|self + _no)
             76 LOAD_DEREF               2 (mpath)
             78 LOAD_FAST                1 (p)
             80 LOAD_CONST               1 ('expecting string ')
             82 LOAD_DEREF               3 (name)
             84 FORMAT_VALUE             0
             86 BUILD_STRING             2
             88 CALL                     3

        >>   96 RETURN_VALUE

#
# json model 7
#
              0 COPY_FREE_VARS           3

              2 RESUME                   0
              4 LOAD_GLOBAL              1 (NULL + isinstance)
             14 LOAD_FAST                0 (v)
             16 LOAD_GLOBAL              2 (str)
             26 CALL                     2
             34 COPY                     1
             36 POP_JUMP_IF_FALSE        5 (to 48)
             38 POP_TOP
             40 LOAD_FAST                0 (v)
             42 LOAD_DEREF               3 (name)
             44 COMPARE_OP              40 (==)
        >>   48 COPY                     1
             50 POP_JUMP_IF_TRUE        22 (to 96)
             52 POP_TOP

             54 LOAD_DEREF               4 (self)
             56 LOAD_ATTR                5 (NULL|self + _no)
             76 LOAD_DEREF               2 (mpath)
             78 LOAD_FAST                1 (p)
             80 LOAD_CONST               1 ('expecting string ')
             82 LOAD_DEREF               3 (name)
             84 FORMAT_VALUE             0
             86 BUILD_STRING             2
             88 CALL                     3

        >>   96 RETURN_VALUE

#
# json model 8
#
              0 COPY_FREE_VARS           3

              2 RESUME                   0
              4 LOAD_GLOBAL              1 (NULL + isinstance)
             14 LOAD_FAST                0 (v)
             16 LOAD_GLOBAL              2 (str)
             26 CALL                     2
             34 COPY                     1
             36 POP_JUMP_IF_FALSE        5 (to 48)
             38 POP_TOP
             40 LOAD_FAST                0 (v)
             42 LOAD_DEREF               3 (name)
             44 COMPARE_OP              40 (==)
        >>   48 COPY                     1
             50 POP_JUMP_IF_TRUE        22 (to 96)
             52 POP_TOP

             54 LOAD_DEREF               4 (self)
             56 LOAD_ATTR                5 (NULL|self + _no)
             76 LOAD_DEREF               2 (mpath)
             78 LOAD_FAST                1 (p)
             80 LOAD_CONST               1 ('expecting string ')
             82 LOAD_DEREF               3 (name)
             84 FORMAT_VALUE             0
             86 BUILD_STRING             2
             88 CALL                     3

        >>   96 RETURN_VALUE

